README.txt
setup.cfg
setup.py
geolucidate/__init__.py
geolucidate/functions.py
geolucidate/parser.py
geolucidate.egg-info/PKG-INFO
geolucidate.egg-info/SOURCES.txt
geolucidate.egg-info/dependency_links.txt
geolucidate.egg-info/top_level.txt
geolucidate/links/__init__.py
geolucidate/links/bing.py
geolucidate/links/google.py
geolucidate/links/osm.py
geolucidate/links/tools.py
geolucidate/links/yahoo.py
geolucidate/tests/__init__.py
geolucidate/tests/tests.py