Metadata-Version: 1.0
Name: geolucidate
Version: 0.4
Summary: Parse free-form geographic coordinates in text, and automatically generate links and metadata.
Home-page: http://github.com/kurtraschke/geolucidate
Author: Kurt Raschke
Author-email: kurt@kurtraschke.com
License: MIT
Platform: UNKNOWN
Classifier: Development Status :: 5 - Production/Stable
Classifier: Intended Audience :: Developers
Classifier: License :: OSI Approved :: MIT License
Classifier: Programming Language :: Python
Classifier: Topic :: Internet
Classifier: Topic :: Text Processing :: Filters
Classifier: Topic :: Text Processing :: Markup :: HTML
Classifier: Topic :: Scientific/Engineering :: GIS
